{"totalStudents": 8, "newStudents": 8, "oldStudents": 0, "todayIncome": 604400.0, "weeklyIncome": 1462600.0, "monthlyIncome": 1462600.0, "pendingCourse": 0, "pendingBooks": 34622.0, "pendingTransport": 445000.0, "pendingFees": 38222.0, "todayCourse": 219400.0, "todayBooks": 2000.0, "todayTransport": 383000.0, "todayAccessories": 0, "weeklyCourse": 739400.0, "weeklyBooks": 10200.0, "weeklyTransport": 713000.0, "weeklyAccessories": 0, "monthlyCourse": 739400.0, "monthlyBooks": 10200.0, "monthlyTransport": 713000.0, "monthlyAccessories": 0, "categoryBreakdowns": {"today": {"All": {"cash": 236900.0, "upi": 337500.0, "bank": 30000.0, "cards": 0.0, "swiping": 0.0}, "Course": {"cash": 108400.0, "upi": 111000.0, "bank": 0.0, "cards": 0.0, "swiping": 0.0}, "Books": {"cash": 2000.0, "upi": 0.0, "bank": 0.0, "cards": 0.0, "swiping": 0.0}, "Transport": {"cash": 126500.0, "upi": 226500.0, "bank": 30000.0, "cards": 0.0, "swiping": 0.0}, "Accessory": {"cash": 0.0, "upi": 0.0, "bank": 0.0, "cards": 0.0, "swiping": 0.0}}, "week": {"All": {"cash": 585300.0, "upi": 847300.0, "bank": 30000.0, "cards": 0.0, "swiping": 0.0}, "Course": {"cash": 456800.0, "upi": 282600.0, "bank": 0.0, "cards": 0.0, "swiping": 0.0}, "Books": {"cash": 2000.0, "upi": 8200.0, "bank": 0.0, "cards": 0.0, "swiping": 0.0}, "Transport": {"cash": 126500.0, "upi": 556500.0, "bank": 30000.0, "cards": 0.0, "swiping": 0.0}, "Accessory": {"cash": 0.0, "upi": 0.0, "bank": 0.0, "cards": 0.0, "swiping": 0.0}}, "month": {"All": {"cash": 585300.0, "upi": 847300.0, "bank": 30000.0, "cards": 0.0, "swiping": 0.0}, "Course": {"cash": 456800.0, "upi": 282600.0, "bank": 0.0, "cards": 0.0, "swiping": 0.0}, "Books": {"cash": 2000.0, "upi": 8200.0, "bank": 0.0, "cards": 0.0, "swiping": 0.0}, "Transport": {"cash": 126500.0, "upi": 556500.0, "bank": 30000.0, "cards": 0.0, "swiping": 0.0}, "Accessory": {"cash": 0.0, "upi": 0.0, "bank": 0.0, "cards": 0.0, "swiping": 0.0}}}, "monthlyChartData": [{"name": "Jan", "amount": 0, "displayLabel": "\u20b90", "amountFormatted": "\u20b90"}, {"name": "Feb", "amount": 0, "displayLabel": "\u20b90", "amountFormatted": "\u20b90"}, {"name": "Mar", "amount": 0, "displayLabel": "\u20b90", "amountFormatted": "\u20b90"}, {"name": "Apr", "amount": 0, "displayLabel": "\u20b90", "amountFormatted": "\u20b90"}, {"name": "May", "amount": 858200.0, "displayLabel": "\u20b9858k", "amountFormatted": "\u20b9858,200"}, {"name": "Jun", "amount": 604400.0, "displayLabel": "\u20b9604k", "amountFormatted": "\u20b9604,400"}], "lastUpdated": "2026-06-01T15:57:42.968696+00:00"}