{"totalStudents": 0, "newStudents": 0, "oldStudents": 0, "todayIncome": 0.0, "weeklyIncome": 0.0, "monthlyIncome": 0.0, "pendingFees": 63500.0, "monthlyChartData": [{"name": "Dec", "amount": 0, "displayLabel": "\u20b90", "amountFormatted": "\u20b90"}, {"name": "Jan", "amount": 0, "displayLabel": "\u20b90", "amountFormatted": "\u20b90"}, {"name": "Feb", "amount": 0.0, "displayLabel": "\u20b90", "amountFormatted": "\u20b90"}, {"name": "Mar", "amount": 0, "displayLabel": "\u20b90", "amountFormatted": "\u20b90"}, {"name": "Apr", "amount": 0, "displayLabel": "\u20b90", "amountFormatted": "\u20b90"}, {"name": "May", "amount": 0, "displayLabel": "\u20b90", "amountFormatted": "\u20b90"}], "lastUpdated": "2026-05-22T00:46:27.369924"}